pancakeswap_py/__init__.py
pancakeswap_py/constant.py
pancakeswap_py/py.typed
pancakeswap_py/v2.py
pancakeswap_py/v3.py
pancakeswap_py-0.1.6.dist-info/METADATA
pancakeswap_py-0.1.6.dist-info/WHEEL
pancakeswap_py-0.1.6.dist-info/RECORD
