Metadata-Version: 2.4
Name: pancakeswap-py
Version: 0.1.6
Summary: A concise PancakeSwap V2/V3 Python library
Project-URL: Homepage, https://github.com/ZHUZIOK/pancakeswap-py
Project-URL: Repository, https://github.com/ZHUZIOK/pancakeswap-py
Project-URL: Bug Tracker, https://github.com/ZHUZIOK/pancakeswap-py/issues
Project-URL: Documentation, https://github.com/ZHUZIOK/pancakeswap-py#readme
Author-email: ZHUZIOK <a1349089572@gmail.com>
Requires-Python: >=3.10
Requires-Dist: pydantic>=2.11.7
Requires-Dist: web3>=7.12.0
